pysimba/__init__.py
pysimba/utils.py
pysimba/client/__init__.py
pysimba/client/core.py
pysimba/client/errors.py
pysimba/client/mixins.py
pysimba/client/utils.py
pysimba/entities/__init__.py
pysimba/entities/ad.py
pysimba/entities/campaign.py
pysimba/entities/creative.py
pysimba/entities/customer.py
pysimba/entities/keyword.py
pysimba/insight/__init__.py
pysimba/insight/core.py
pysimba/reporting/__init__.py
pysimba/reporting/core.py
pysimba/targeting/__init__.py
pysimba/targeting/audience.py
pysimba/targeting/content.py
pysimba/targeting/device.py
pysimba/targeting/location.py
pysimba-1.1.0.dist-info/LICENSE
pysimba-1.1.0.dist-info/METADATA
pysimba-1.1.0.dist-info/WHEEL
pysimba-1.1.0.dist-info/top_level.txt
pysimba-1.1.0.dist-info/RECORD
