Metadata-Version: 2.1
Name: pysimba
Version: 1.1.0
Summary: SDK for "https://subway.simba.taobao.com"
Home-page: https://github.com/zuanzuan1992/pysimba
Author: Shuangzuan He
Author-email: zuanzuan1992@gmail.com
License: UNKNOWN
Platform: UNKNOWN
Classifier: Programming Language :: Python :: 3
Classifier: License :: OSI Approved :: MIT License
Classifier: Operating System :: OS Independent
